Workbook

Sheet Revenue Forecast
A1: Month | B1: Product A | C1: Product B | D1: Product C | E1: Total | F1: YoY Growth | G1: Cumulative
A2: Jan | B2: 120000 | C2: 85000 | D2: 45000 | E2: =SUM(B2:D2) | F2: 0.12 | G2: =E2
A3: Feb | B3: 135000 | C3: 92000 | D3: 52000 | E3: =SUM(B3:D3) | F3: 0.15 | G3: =G2+E3
A4: Mar | B4: 142000 | C4: 78000 | D4: 48000 | E4: =SUM(B4:D4) | F4: 0.08 | G4: =G3+E4
A5: Apr | B5: 128000 | C5: 95000 | D5: 55000 | E5: =SUM(B5:D5) | F5: 0.18 | G5: =G4+E5
A6: May | B6: 155000 | C6: 88000 | D6: 62000 | E6: =SUM(B6:D6) | F6: 0.22 | G6: =G5+E6
A7: Jun | B7: 168000 | C7: 102000 | D7: 58000 | E7: =SUM(B7:D7) | F7: 0.14 | G7: =G6+E7
A8: Jul | B8: 145000 | C8: 97000 | D8: 67000 | E8: =SUM(B8:D8) | F8: 0.11 | G8: =G7+E8
A9: Aug | B9: 152000 | C9: 105000 | D9: 72000 | E9: =SUM(B9:D9) | F9: 0.19 | G9: =G8+E9
A10: Sep | B10: 178000 | C10: 112000 | D10: 68000 | E10: =SUM(B10:D10) | F10: 0.25 | G10: =G9+E10
A11: Oct | B11: 192000 | C11: 98000 | D11: 75000 | E11: =SUM(B11:D11) | F11: 0.16 | G11: =G10+E11
A12: Nov | B12: 185000 | C12: 115000 | D12: 82000 | E12: =SUM(B12:D12) | F12: 0.13 | G12: =G11+E12
A13: Dec | B13: 210000 | C13: 125000 | D13: 95000 | E13: =SUM(B13:D13) | F13: 0.21 | G13: =G12+E13
A14: TOTAL | B14: =SUM(B2:B13) | C14: =SUM(C2:C13) | D14: =SUM(D2:D13) | E14: =SUM(E2:E13)

Sheet Cost Allocation
A1: Department | B1: Headcount | C1: Avg Salary | D1: Benefits Rate | E1: Total Comp | F1: Overhead % | G1: Fully Loaded | H1: Revenue Share
A2: Engineering | B2: 45 | C2: 142000 | D2: 0.32 | E2: =B2*C2*(1+D2) | F2: 0.15 | G2: =E2*(1+F2) | H2: =G2/'Revenue Forecast'!E14
A3: Sales | B3: 28 | C3: 95000 | D3: 0.28 | E3: =B3*C3*(1+D3) | F3: 0.22 | G3: =E3*(1+F3) | H3: =G3/'Revenue Forecast'!E14
A4: Marketing | B4: 15 | C4: 88000 | D4: 0.25 | E4: =B4*C4*(1+D4) | F4: 0.18 | G4: =E4*(1+F4) | H4: =G4/'Revenue Forecast'!E14
A5: Finance | B5: 8 | C5: 105000 | D5: 0.3 | E5: =B5*C5*(1+D5) | F5: 0.1 | G5: =E5*(1+F5) | H5: =G5/'Revenue Forecast'!E14
A6: HR | B6: 6 | C6: 92000 | D6: 0.28 | E6: =B6*C6*(1+D6) | F6: 0.08 | G6: =E6*(1+F6) | H6: =G6/'Revenue Forecast'!E14
A7: Operations | B7: 18 | C7: 85000 | D7: 0.25 | E7: =B7*C7*(1+D7) | F7: 0.2 | G7: =E7*(1+F7) | H7: =G7/'Revenue Forecast'!E14
A8: Executive | B8: 4 | C8: 225000 | D8: 0.35 | E8: =B8*C8*(1+D8) | F8: 0.05 | G8: =E8*(1+F8) | H8: =G8/'Revenue Forecast'!E14

Sheet Vendor Contracts
A1: Vendor | B1: Annual Cost | C1: Users | D1: Cost/User | E1: Contract End | F1: Auto-Renew | G1: Utilization | H1: Risk Score
A2: Salesforce | B2: 285000 | C2: 28 | D2: =B2/C2 | E2: 2025-12-31 | F2: Yes | G2: 0.72 | H2: =IF(AND(G2<0.5,F2="Yes"),"HIGH",IF(G2<0.5,"MEDIUM",IF(AND(G2>0.8,B2<50000),"LOW","MEDIUM")))
A3: Microsoft 365 | B3: 156000 | C3: 124 | D3: =B3/C3 | E3: 2026-03-15 | F3: Yes | G3: 0.91 | H3: =IF(AND(G3<0.5,F3="Yes"),"HIGH",IF(G3<0.5,"MEDIUM",IF(AND(G3>0.8,B3<50000),"LOW","MEDIUM")))
A4: AWS | B4: 480000 | C4: 45 | D4: =B4/C4 | E4: 2025-06-30 | F4: No | G4: 0.65 | H4: =IF(AND(G4<0.5,F4="Yes"),"HIGH",IF(G4<0.5,"MEDIUM",IF(AND(G4>0.8,B4<50000),"LOW","MEDIUM")))
A5: Slack | B5: 42000 | C5: 124 | D5: =B5/C5 | E5: 2025-09-30 | F5: Yes | G5: 0.88 | H5: =IF(AND(G5<0.5,F5="Yes"),"HIGH",IF(G5<0.5,"MEDIUM",IF(AND(G5>0.8,B5<50000),"LOW","MEDIUM")))
A6: Jira | B6: 36000 | C6: 65 | D6: =B6/C6 | E6: 2026-01-31 | F6: Yes | G6: 0.78 | H6: =IF(AND(G6<0.5,F6="Yes"),"HIGH",IF(G6<0.5,"MEDIUM",IF(AND(G6>0.8,B6<50000),"LOW","MEDIUM")))
A7: Zoom | B7: 28000 | C7: 124 | D7: =B7/C7 | E7: 2025-08-15 | F7: Yes | G7: 0.45 | H7: =IF(AND(G7<0.5,F7="Yes"),"HIGH",IF(G7<0.5,"MEDIUM",IF(AND(G7>0.8,B7<50000),"LOW","MEDIUM")))
A8: HubSpot | B8: 72000 | C8: 15 | D8: =B8/C8 | E8: 2025-11-30 | F8: Yes | G8: 0.52 | H8: =IF(AND(G8<0.5,F8="Yes"),"HIGH",IF(G8<0.5,"MEDIUM",IF(AND(G8>0.8,B8<50000),"LOW","MEDIUM")))
A9: Datadog | B9: 96000 | C9: 12 | D9: =B9/C9 | E9: 2026-02-28 | F9: No | G9: 0.83 | H9: =IF(AND(G9<0.5,F9="Yes"),"HIGH",IF(G9<0.5,"MEDIUM",IF(AND(G9>0.8,B9<50000),"LOW","MEDIUM")))
A10: DocuSign | B10: 18000 | C10: 35 | D10: =B10/C10 | E10: 2025-07-31 | F10: Yes | G10: 0.35 | H10: =IF(AND(G10<0.5,F10="Yes"),"HIGH",IF(G10<0.5,"MEDIUM",IF(AND(G10>0.8,B10<50000),"LOW","MEDIUM")))
A11: Figma | B11: 24000 | C11: 8 | D11: =B11/C11 | E11: 2025-10-31 | F11: Yes | G11: 0.9 | H11: =IF(AND(G11<0.5,F11="Yes"),"HIGH",IF(G11<0.5,"MEDIUM",IF(AND(G11>0.8,B11<50000),"LOW","MEDIUM")))

Sheet Assumptions
A1: ASSUMPTIONS — DO NOT MODIFY
A3: Parameter | B3: Value | C3: Last Updated | D3: Updated By
A4: Tax Rate | B4: 0.21 | C4: 2022-01-15 | D4: jsmith
A5: Discount Rate | B5: 0.08 | C5: 2021-06-30 | D5: UNKNOWN
A6: Growth Target | B6: 0.15 | C6: 2023-03-01 | D6: cfo_direct
A7: Inflation Adj | B7: 0.035 | C7: 2020-12-01 | D7: UNKNOWN
A8: FX Rate EUR/USD | B8: 1.08 | C8: 2024-02-15 | D8: treasury
A9: Benefits Load | B9: 0.3 | C9: 2019-08-22 | D9: hr_admin
A10: Contingency % | B10: 0.1 | C10: 2021-11-01 | D10: UNKNOWN

Sheet Summary
A1: EXECUTIVE SUMMARY
A3: Total Revenue | B3: ='Revenue Forecast'!E14
A4: Total Costs | B4: =SUM('Cost Allocation'!G2:G8)
A5: Gross Margin | B5: =B3-B4
A6: Margin % | B6: =B5/B3
A8: Vendor Spend | B8: =SUM('Vendor Contracts'!B2:B11)
A9: Vendor % of Revenue | B9: =B8/B3
A11: Adjusted Margin (after assumptions) | B11: =B5*(1-Assumptions!B7)*(1+Assumptions!B4)
